tests/integration/__init__.py
tests/integration/asserts.py
tests/integration/conftest.py
tests/integration/test_integration_access_token.py
tests/integration/test_integration_account_plans.py
tests/integration/test_integration_account_users.py
tests/integration/test_integration_accounts.py
tests/integration/test_integration_activedocs.py
tests/integration/test_integration_analytics.py
tests/integration/test_integration_api_client.py
tests/integration/test_integration_application.py
tests/integration/test_integration_application_plan.py
tests/integration/test_integration_backend_mapping_rules.py
tests/integration/test_integration_backend_methods.py
tests/integration/test_integration_backend_metrics.py
tests/integration/test_integration_backend_usages.py
tests/integration/test_integration_backends.py
tests/integration/test_integration_cms.py
tests/integration/test_integration_custom_tenant.py
tests/integration/test_integration_default_client.py
tests/integration/test_integration_fields_definitions.py
tests/integration/test_integration_invoices.py
tests/integration/test_integration_limit.py
tests/integration/test_integration_mapping_rules.py
tests/integration/test_integration_methods.py
tests/integration/test_integration_metrics.py
tests/integration/test_integration_policies.py
tests/integration/test_integration_pricing_rules.py
tests/integration/test_integration_provider_account.py
tests/integration/test_integration_provider_account_users.py
tests/integration/test_integration_response_headers.py
tests/integration/test_integration_service_plans.py
tests/integration/test_integration_service_subscriptions.py
tests/integration/test_integration_services.py
tests/integration/test_integration_tenant.py
tests/integration/test_integration_webhook.py
tests/integration/auth/__init__.py
tests/integration/auth/test_app_key.py
tests/integration/auth/test_app_key_authorization.py
tests/integration/auth/test_different_app_key_name.py
3scale_api-0.35.3.dist-info/LICENSE
3scale_api-0.35.3.dist-info/METADATA
3scale_api-0.35.3.dist-info/WHEEL
3scale_api-0.35.3.dist-info/top_level.txt
3scale_api-0.35.3.dist-info/RECORD
