Metadata-Version: 2.1
Name: 3scale-api
Version: 0.35.3
Summary: 3scale API python client
Home-page: https://github.com/3scale-qe/3scale-api-python
Author: Peter Stanko
Author-email: stanko@mail.muni.cz
Maintainer: Matej Dujava
Maintainer-email: mdujava@redhat.com
Classifier: Operating System :: OS Independent
Classifier: License :: OSI Approved :: Apache Software License
Classifier: Intended Audience :: Developers
Classifier: Topic :: Utilities
Classifier: Programming Language :: Python :: 3
Classifier: Programming Language :: Python :: 3.7
Classifier: Programming Language :: Python :: 3.8
Classifier: Programming Language :: Python :: 3.9
Classifier: Programming Language :: Python :: 3.10
Classifier: Programming Language :: Python :: 3.11
Classifier: Programming Language :: Python :: 3.12
Classifier: Programming Language :: Python :: 3.13
License-File: LICENSE
Requires-Dist: requests
Requires-Dist: backoff
Provides-Extra: dev
Requires-Dist: pytest; extra == "dev"
Requires-Dist: coverage; extra == "dev"
Requires-Dist: python-dotenv; extra == "dev"
Requires-Dist: responses; extra == "dev"
Provides-Extra: docs
Requires-Dist: sphinx; extra == "docs"
